pyronot/__init__.py
pyronot/_robot.py
pyronot/_robot_srdf_parser.py
pyronot/_robot_urdf_parser.py
pyronot/utils.py
pyronot/collision/__init__.py
pyronot/collision/_collision.py
pyronot/collision/_geometry.py
pyronot/collision/_geometry_pairs.py
pyronot/collision/_neural_collision.py
pyronot/collision/_robot_collision.py
pyronot/collision/_utils.py
pyronot/costs/__init__.py
pyronot/costs/_costs.py
pyronot/costs/_pose_cost_analytic_jac.py
pyronot/costs/_pose_cost_numerical_jac.py
pyronot/viewer/__init__.py
pyronot/viewer/_batched_urdf.py
pyronot/viewer/_manipulability_ellipse.py
pyronot/viewer/_weight_tuner.py
pyronot-0.1.0.dist-info/licenses/LICENSE
pyronot-0.1.0.dist-info/METADATA
pyronot-0.1.0.dist-info/WHEEL
pyronot-0.1.0.dist-info/top_level.txt
pyronot-0.1.0.dist-info/RECORD
