Metadata-Version: 2.4
Name: pyronot
Version: 0.1.0
Summary: Python Robot Kinematics Library
License: MIT
Classifier: Programming Language :: Python :: 3.10
Classifier: Programming Language :: Python :: 3.11
Classifier: Programming Language :: Python :: 3.12
Classifier: Programming Language :: Python :: 3.13
Classifier: License :: OSI Approved :: MIT License
Classifier: Operating System :: OS Independent
Requires-Python: >=3.10
License-File: LICENSE
Requires-Dist: tyro
Requires-Dist: jax>=0.4.0
Requires-Dist: jaxlib
Requires-Dist: jaxlie>=1.0.0
Requires-Dist: jax_dataclasses>=1.0.0
Requires-Dist: jaxtyping
Requires-Dist: loguru
Requires-Dist: robot_descriptions
Requires-Dist: yourdfpy
Requires-Dist: trimesh
Requires-Dist: viser
Requires-Dist: pyliblzfse
Provides-Extra: dev
Requires-Dist: pyright>=1.1.308; extra == "dev"
Requires-Dist: scikit-sparse; extra == "dev"
Requires-Dist: ruff; extra == "dev"
Requires-Dist: pytest; extra == "dev"
Requires-Dist: m2r2; extra == "dev"
Dynamic: license-file
